denovowest/__init__.py
denovowest/cli.py
denovowest/annotations/__init__.py
denovowest/annotations/annotate_cadd.py
denovowest/annotations/annotate_constraint.py
denovowest/annotations/annotate_custom.py
denovowest/annotations/annotate_dbnsfp.py
denovowest/annotations/annotate_gnomad.py
denovowest/annotations/annotate_shet.py
denovowest/annotations/annotate_vcf.py
denovowest/annotations/rates_to_vcf.py
denovowest/dnm/__init__.py
denovowest/dnm/filter_dnm.py
denovowest/rates/__init__.py
denovowest/rates/create_rates_file.py
denovowest/rates/rates_stats.py
denovowest/rates/summarize_stats.py
denovowest/simulation/__init__.py
denovowest/simulation/probabilities.py
denovowest/simulation/scores.py
denovowest/simulation/simulation.py
denovowest/utils/__init__.py
denovowest/utils/io_helpers.py
denovowest/utils/log.py
denovowest/utils/params.py
denovowest-0.1.2.dist-info/licenses/LICENSE
denovowest-0.1.2.dist-info/METADATA
denovowest-0.1.2.dist-info/WHEEL
denovowest-0.1.2.dist-info/entry_points.txt
denovowest-0.1.2.dist-info/top_level.txt
denovowest-0.1.2.dist-info/RECORD
