Metadata-Version: 2.4
Name: denovowest
Version: 0.1.2
Summary: A de novo mutation simulation framework
Author: Joanna Kaplanis, Kaitlin Samocha
Author-email: Erwan Delage <ed11@sanger.ac.uk>
License: MIT License
Classifier: Programming Language :: Python :: 3
Classifier: License :: OSI Approved :: MIT License
Classifier: Operating System :: OS Independent
Classifier: Intended Audience :: Science/Research
Classifier: Topic :: Scientific/Engineering :: Bio-Informatics
Requires-Python: >=3.8
License-File: LICENSE
Requires-Dist: numpy
Requires-Dist: scipy
Requires-Dist: pandas
Requires-Dist: gffutils
Requires-Dist: click
Requires-Dist: pyyaml
Requires-Dist: pysam
Requires-Dist: joblib
Dynamic: license-file
